serialchemy/__init__.py
serialchemy/_version.py
serialchemy/conftest.py
serialchemy/datetime_serializer.py
serialchemy/enum_field.py
serialchemy/enum_serializer.py
serialchemy/field.py
serialchemy/func.py
serialchemy/model_serializer.py
serialchemy/nested_fields.py
serialchemy/polymorphic_serializer.py
serialchemy/serializer.py
serialchemy/serializer_checks.py
serialchemy/_tests/__init__.py
serialchemy/_tests/sample_model.py
serialchemy/_tests/test_datetimeserializer.py
serialchemy/_tests/test_field.py
serialchemy/_tests/test_func.py
serialchemy/_tests/test_nested_fields.py
serialchemy/_tests/test_polymorphic_serializer.py
serialchemy/_tests/test_readme.py
serialchemy/_tests/test_serialization.py
serialchemy/_tests/sample_model_imperative/model.py
serialchemy/_tests/sample_model_imperative/orm_mapping.py
serialchemy/_tests/test_func/test_dump.yml
serialchemy/_tests/test_nested_fields/test_custom_serializer_EmployeeSerializerNestedAttrsFields.yml
serialchemy/_tests/test_nested_fields/test_custom_serializer_EmployeeSerializerNestedModelFields.yml
serialchemy/_tests/test_nested_fields/test_deserialize_with_custom_serializer_declarative_.yml
serialchemy/_tests/test_nested_fields/test_deserialize_with_custom_serializer_imperative_.yml
serialchemy/_tests/test_nested_fields/test_dump_with_nested_polymorphic_declarative_.yml
serialchemy/_tests/test_nested_fields/test_dump_with_nested_polymorphic_imperative_.yml
serialchemy/_tests/test_nested_fields/test_load_with_nested_polymorphic_same_table_pk_names.yml
serialchemy/_tests/test_nested_fields/test_load_with_nested_polymorphic_with_different_table_pk_names_declarative_.yml
serialchemy/_tests/test_nested_fields/test_load_with_nested_polymorphic_with_different_table_pk_names_imperative_.yml
serialchemy/_tests/test_serialization/test_dump_choice_type.yml
serialchemy/_tests/test_serialization/test_enum_key_field_dump.yml
serialchemy/_tests/test_serialization/test_enum_key_field_load.yml
serialchemy-1.0.3.dist-info/licenses/LICENSE
serialchemy-1.0.3.dist-info/METADATA
serialchemy-1.0.3.dist-info/WHEEL
serialchemy-1.0.3.dist-info/top_level.txt
serialchemy-1.0.3.dist-info/RECORD
