Metadata-Version: 2.4
Name: serialchemy
Version: 1.0.3
Summary: Serializers for SQLAlchemy models.
Author-email: ESSS <foss@esss.co>
License-Expression: MIT
Project-URL: Repository, https://github.com/ESSS/serialchemy
Project-URL: Issues, https://github.com/ESSS/serialchemy/issues
Keywords: serialchemy,serializer,sqlalchemy
Classifier: Development Status :: 3 - Alpha
Classifier: Intended Audience :: Developers
Classifier: Programming Language :: Python :: 3.10
Classifier: Programming Language :: Python :: 3.11
Classifier: Programming Language :: Python :: 3.12
Classifier: Programming Language :: Python :: 3.13
Requires-Python: >=3.10
License-File: LICENSE
Requires-Dist: sqlalchemy<3.0,>=1.4
Provides-Extra: docs
Requires-Dist: sphinx>=1.4; extra == "docs"
Requires-Dist: sphinx_rtd_theme; extra == "docs"
Requires-Dist: sphinx-autodoc-typehints; extra == "docs"
Requires-Dist: typing_extensions; extra == "docs"
Provides-Extra: testing
Requires-Dist: codecov; extra == "testing"
Requires-Dist: mypy; extra == "testing"
Requires-Dist: pytest; extra == "testing"
Requires-Dist: pytest-cov; extra == "testing"
Requires-Dist: pytest-regressions; extra == "testing"
Requires-Dist: pytest-freezegun; extra == "testing"
Requires-Dist: pre-commit; extra == "testing"
Requires-Dist: setuptools; extra == "testing"
Requires-Dist: sqlalchemy_utils; extra == "testing"
Requires-Dist: tox; extra == "testing"
Dynamic: license-file
